rindegastos_revops/__init__.py
rindegastos_revops/data_engineering/__init__.py
rindegastos_revops/data_engineering/pandas_helpers.py
rindegastos_revops/data_engineering/shema_formater.py
rindegastos_revops/hubspot_api/__init__.py
rindegastos_revops/hubspot_api/account/__init__.py
rindegastos_revops/hubspot_api/account/users/__init__.py
rindegastos_revops/hubspot_api/account/users/all.py
rindegastos_revops/hubspot_api/account/users/teams.py
rindegastos_revops/hubspot_api/helpers/__init__.py
rindegastos_revops/hubspot_api/helpers/dates.py
rindegastos_revops/hubspot_api/helpers/file_name.py
rindegastos_revops/hubspot_api/helpers/get_dataframe.py
rindegastos_revops/hubspot_api/helpers/hubspot.py
rindegastos_revops/hubspot_api/objects/__init__.py
rindegastos_revops/hubspot_api/objects/associations.py
rindegastos_revops/hubspot_api/objects/base_read.py
rindegastos_revops/hubspot_api/objects/base_read_one.py
rindegastos_revops/hubspot_api/objects/base_search.py
rindegastos_revops/hubspot_api/owners/__init__.py
rindegastos_revops/hubspot_api/owners/read.py
rindegastos_revops/hubspot_api/pipelines/__init__.py
rindegastos_revops/hubspot_api/pipelines/read.py
rindegastos_revops/hubspot_api/properties/__init__.py
rindegastos_revops/hubspot_api/properties/read_all.py
rindegastos_revops/zendesk_api/__init__.py
rindegastos_revops/zendesk_api/base_request.py
rindegastos_revops/zendesk_api/endpoints.py
rindegastos_revops/zendesk_api/get_all.py
rindegastos_revops-0.0.26.dist-info/METADATA
rindegastos_revops-0.0.26.dist-info/WHEEL
rindegastos_revops-0.0.26.dist-info/top_level.txt
rindegastos_revops-0.0.26.dist-info/RECORD
