Metadata-Version: 2.1
Name: rindegastos_revops
Version: 0.0.26
Summary: Simple sdk for revops packages
Home-page: https://github.com/joigmz/rindegastos_revops
Author: Jose Izam
Author-email: jose.izam99@gmail.com
Project-URL: Bug Tracker, https://github.com/joigmz/rindegastos_revops
Classifier: Programming Language :: Python :: 3
Classifier: License :: OSI Approved :: MIT License
Classifier: Operating System :: OS Independent
Requires-Python: >=3.7
Requires-Dist: requests
Requires-Dist: pandas
